Metadata-Version: 2.1
Name: snydlyprojects
Version: 1.0.3
Summary: My collection of personal projects I'm currently working on for personal development
Home-page: UNKNOWN
Author: Dylan Snyder
Author-email: dylansnyder711@gmail.com
License: MIT
Keywords: private personal project
Platform: UNKNOWN
Classifier: Development Status :: 5 - Production/Stable
Classifier: Intended Audience :: Education
Classifier: Operating System :: Microsoft :: Windows :: Windows 10
Classifier: License :: OSI Approved :: MIT License
Classifier: Programming Language :: Python :: 3
License-File: LICENSE.txt
